imio.directory.core-1.2.25-py3.13-nspkg.pth
imio/directory/core/__init__.py
imio/directory/core/config.py
imio/directory/core/configure.zcml
imio/directory/core/converters.py
imio/directory/core/indexers.py
imio/directory/core/indexers.zcml
imio/directory/core/interfaces.py
imio/directory/core/monkey.py
imio/directory/core/monkey.zcml
imio/directory/core/overrides.zcml
imio/directory/core/permissions.zcml
imio/directory/core/profiles.zcml
imio/directory/core/setuphandlers.py
imio/directory/core/subscribers.py
imio/directory/core/subscribers.zcml
imio/directory/core/testing.py
imio/directory/core/utils.py
imio/directory/core/vocabularies.py
imio/directory/core/vocabularies.zcml
imio/directory/core/browser/__init__.py
imio/directory/core/browser/configure.zcml
imio/directory/core/browser/import.pt
imio/directory/core/browser/import.py
imio/directory/core/browser/utils.py
imio/directory/core/browser/overrides/.gitkeep
imio/directory/core/browser/static/.gitkeep
imio/directory/core/browser/static/Makefile
imio/directory/core/browser/static/directory-edit-compiled.js
imio/directory/core/browser/static/package.json
imio/directory/core/browser/static/webpack.config.js
imio/directory/core/browser/static/src/edit.js
imio/directory/core/browser/static/src/edit.less
imio/directory/core/contents/__init__.py
imio/directory/core/contents/configure.zcml
imio/directory/core/contents/contact/__init__.py
imio/directory/core/contents/contact/configure.zcml
imio/directory/core/contents/contact/content.py
imio/directory/core/contents/contact/forms.py
imio/directory/core/contents/contact/serializer.py
imio/directory/core/contents/contact/view.pt
imio/directory/core/contents/contact/view.py
imio/directory/core/contents/entity/__init__.py
imio/directory/core/contents/entity/configure.zcml
imio/directory/core/contents/entity/content.py
imio/directory/core/contents/entity/export.py
imio/directory/core/faceted/config/entity.xml
imio/directory/core/profiles/default/actions.xml
imio_directory_core-1.2.25.dist-info/licenses/LICENSE.GPL
imio_directory_core-1.2.25.dist-info/licenses/LICENSE.rst
imio_directory_core-1.2.25.dist-info/METADATA
imio_directory_core-1.2.25.dist-info/WHEEL
imio_directory_core-1.2.25.dist-info/namespace_packages.txt
imio_directory_core-1.2.25.dist-info/top_level.txt
imio_directory_core-1.2.25.dist-info/RECORD
