Metadata-Version: 2.4
Name: imio.directory.core
Version: 1.2.25
Summary: Core product for iMio contacts Directory websites
Home-page: https://github.com/imio/imio.directory.core
Author: Christophe Boulanger
Author-email: christophe.boulanger@imio.be
License: GPL version 2
Project-URL: PyPI, https://pypi.python.org/pypi/imio.directory.core
Project-URL: Source, https://github.com/imio/imio.directory.core
Project-URL: Tracker, https://github.com/imio/imio.directory.core/issues
Keywords: Python Plone CMS
Classifier: Environment :: Web Environment
Classifier: Framework :: Plone
Classifier: Framework :: Plone :: Addon
Classifier: Framework :: Plone :: 6.0
Classifier: Framework :: Plone :: 6.1
Classifier: Programming Language :: Python
Classifier: Programming Language :: Python :: 3
Classifier: Programming Language :: Python :: 3.10
Classifier: Programming Language :: Python :: 3.11
Classifier: Programming Language :: Python :: 3.12
Classifier: Programming Language :: Python :: 3.13
Classifier: Operating System :: OS Independent
Classifier: License :: OSI Approved :: GNU General Public License v2 (GPLv2)
Requires-Python: >=3.10
License-File: LICENSE.GPL
License-File: LICENSE.rst
Requires-Dist: setuptools
Requires-Dist: z3c.jbot
Requires-Dist: z3c.unconfigure
Requires-Dist: plone.api>=1.8.4
Requires-Dist: plone.gallery
Requires-Dist: plone.restapi
Requires-Dist: plone.app.dexterity
Requires-Dist: plone.app.discussion
Requires-Dist: plone.app.imagecropping
Requires-Dist: pandas
Requires-Dist: collective.taxonomy
Requires-Dist: embeddify
Requires-Dist: imio.smartweb.common
Requires-Dist: imio.smartweb.locales
Requires-Dist: collective.instancebehavior
Requires-Dist: collective.z3cform.datagridfield>=2.0
Requires-Dist: collective.geolocationbehavior
Requires-Dist: collective.monkeypatcher
Requires-Dist: collective.schedulefield
Requires-Dist: vobject
Provides-Extra: test
Requires-Dist: plone.app.testing; extra == "test"
Requires-Dist: plone.testing>=5.0.0; extra == "test"
Requires-Dist: plone.app.contenttypes; extra == "test"
Requires-Dist: plone.app.robotframework[debug]; extra == "test"
Requires-Dist: requests-mock; extra == "test"
Requires-Dist: beautifulsoup4; extra == "test"
Requires-Dist: plone.restapi[test]; extra == "test"
Dynamic: author
Dynamic: author-email
Dynamic: classifier
Dynamic: description
Dynamic: home-page
Dynamic: keywords
Dynamic: license
Dynamic: license-file
Dynamic: project-url
Dynamic: provides-extra
Dynamic: requires-dist
Dynamic: requires-python
Dynamic: summary
